weni/protobuf/__init__.py
weni/protobuf/academy/__init__.py
weni/protobuf/academy/user_pb2.py
weni/protobuf/academy/user_pb2_grpc.py
weni/protobuf/connect/__init__.py
weni/protobuf/connect/organization_pb2.py
weni/protobuf/connect/organization_pb2_grpc.py
weni/protobuf/connect/project_pb2.py
weni/protobuf/connect/project_pb2_grpc.py
weni/protobuf/flows/__init__.py
weni/protobuf/flows/billing_pb2.py
weni/protobuf/flows/billing_pb2_grpc.py
weni/protobuf/flows/channel_pb2.py
weni/protobuf/flows/channel_pb2_grpc.py
weni/protobuf/flows/classifier_pb2.py
weni/protobuf/flows/classifier_pb2_grpc.py
weni/protobuf/flows/flow_pb2.py
weni/protobuf/flows/flow_pb2_grpc.py
weni/protobuf/flows/org_pb2.py
weni/protobuf/flows/org_pb2_grpc.py
weni/protobuf/flows/statistic_pb2.py
weni/protobuf/flows/statistic_pb2_grpc.py
weni/protobuf/flows/user_pb2.py
weni/protobuf/flows/user_pb2_grpc.py
weni/protobuf/integrations/__init__.py
weni/protobuf/integrations/user_pb2.py
weni/protobuf/integrations/user_pb2_grpc.py
weni/protobuf/intelligence/__init__.py
weni/protobuf/intelligence/authentication_pb2.py
weni/protobuf/intelligence/authentication_pb2_grpc.py
weni/protobuf/intelligence/organization_pb2.py
weni/protobuf/intelligence/organization_pb2_grpc.py
weni/protobuf/intelligence/repository_pb2.py
weni/protobuf/intelligence/repository_pb2_grpc.py
weni/protobuf/wpp_router/channel_pb2.py
weni/protobuf/wpp_router/channel_pb2_grpc.py
weni_protobuffers-1.2.18.dist-info/WHEEL
weni_protobuffers-1.2.18.dist-info/METADATA
weni_protobuffers-1.2.18.dist-info/RECORD
