Metadata-Version: 2.1
Name: weni-protobuffers
Version: 1.2.18
Summary: Protocol Buffers for Weni Platform
Author: João Carlos
Author-email: jcbalmeida@gmail.com
Requires-Python: >=3.6,<4.0
Classifier: Programming Language :: Python :: 3
Classifier: Programming Language :: Python :: 3.10
Classifier: Programming Language :: Python :: 3.6
Classifier: Programming Language :: Python :: 3.7
Classifier: Programming Language :: Python :: 3.8
Classifier: Programming Language :: Python :: 3.9
Requires-Dist: grpcio (>=1.39.0,<2.0.0)
Requires-Dist: protobuf (>=3.17.3,<4.0.0)
